robokit
