Metadata-Version: 1.0
Name: robokit
Version: 0.0.2
Summary: Minimal implementation of common robotics maths
Home-page: https://github.com/Thomascountz/robokit
Author: Thomas Countz
Author-email: thomascountz@gmail.com
License: MIT
Platform: UNKNOWN
